{
  "version": "1.0",
  "defaultProvider": "filesystem",
  "libraries": [
    {
      "library": "node_modules/admin-lte/plugins/jquery/",
      "files": [ "jquery.min.js" ],
      "destination": "wwwroot/lib/jquery"
    },
    {
      "library": "node_modules/admin-lte/plugins/bootstrap/js/",
      "files": [ "bootstrap.bundle.min.js" ],
      "destination": "wwwroot/lib/bootstrap"
    },
    {
      "library": "node_modules/admin-lte/plugins/fontawesome-free/css/",
      "files": [ "all.min.css" ],
      "destination": "wwwroot/lib/fontawesome"
    },
    {
      "library": "node_modules/admin-lte/plugins/fontawesome-free/webfonts/",
      "destination": "wwwroot/lib/webfonts"
    },
    {
      "library": "node_modules/admin-lte/dist/js/",
      "files": [ "adminlte.min.js" ],
      "destination": "wwwroot/lib/admin-lte"
    },
    {
      "library": "node_modules/admin-lte/dist/css/",
      "files": [ "adminlte.min.css" ],
      "destination": "wwwroot/lib/admin-lte"
    },
    {
      "library": "node_modules/admin-lte/plugins/jquery-ui",
      "files": [ "jquery-ui.min.js" ],
      "destination": "wwwroot/lib/jquery-ui/"
    },
    {
      "library": "node_modules/admin-lte/plugins/select2/css",
      "files": [ "select2.min.css" ],
      "destination": "wwwroot/lib/select2/"
    },
    {
      "library": "node_modules/admin-lte/plugins/select2/js",
      "files": [ "select2.min.js" ],
      "destination": "wwwroot/lib/select2/"
    },
    {
      "library": "node_modules/admin-lte/plugins/select2-bootstrap4-theme",
      "files": [ "select2-bootstrap4.min.css" ],
      "destination": "wwwroot/lib/select2/"
    },
    {
      "provider": "cdnjs",
      "library": "jqueryui-touch-punch@0.2.3",
      "destination": "wwwroot/lib/jquery-ui-touch-punch",
      "files": [ "jquery.ui.touch-punch.min.js" ]
    },
    {
      "provider": "cdnjs",
      "library": "datatables@1.10.19",
      "destination": "wwwroot/lib/datatables",
      "files": [
        "css/dataTables.bootstrap4.min.css",
        "js/jquery.dataTables.min.js",
        "js/dataTables.bootstrap4.min.js"
      ]
    },
    {
      "provider": "cdnjs",
      "library": "fullcalendar@4.2.0",
      "destination": "wwwroot/lib/fullcalendar/",
      "files": [
        "core/main.min.css",
        "core/main.min.js",
        "daygrid/main.min.css",
        "daygrid/main.min.js",
        "timegrid/main.min.css",
        "timegrid/main.min.js",
        "bootstrap/main.min.css",
        "bootstrap/main.min.js",
        "interaction/main.min.js"
      ]
    },
    {
      "provider": "cdnjs",
      "library": "bootswatch@4.4.1",
      "destination": "wwwroot/lib/bootswatch/",
      "files": [
        "cyborg/bootstrap.min.css"
      ]
    },
    {
      "provider": "cdnjs",
      "library": "pivottable@2.23.0",
      "destination": "wwwroot/lib/pivottable/",
      "files": [
        "pivot.min.css",
        "pivot.min.js",
        "plotly_renderers.min.js",
        "export_renderers.min.js",
        "d3_renderers.min.js"
      ]
    },
    {
      "provider": "cdnjs",
      "library": "plotly.js@1.51.1",
      "destination": "wwwroot/lib/plotly/",
      "files": [
        "plotly-basic.min.js"
      ]
    },
    {
      "provider": "cdnjs",
      "library": "d3@5.15.0",
      "destination": "wwwroot/lib/d3/",
      "files": [
        "d3.min.js"
      ]
    },
    {
      "provider": "cdnjs",
      "library": "bootstrap-daterangepicker@3.0.5",
      "destination": "wwwroot/lib/daterangepicker/",
      "files": [
        "daterangepicker.min.css",
        "moment.min.js",
        "daterangepicker.min.js"
      ]
    }
  ]
}